starlit/.env.example
starlit/__init__.py
starlit/config/onboarding.py
starlit/config/settings.py
starlit/config/setup.py
starlit/config/show_help.py
starlit/core/__init__.py
starlit/core/interactive.py
starlit/core/timezone.py
starlit/core/weather_function.py
starlit/core/wind_direction.py
starlit/main.py
starlit/ui/__init__.py
starlit/ui/animations.py
starlit/ui/graphics.py
starlit/ui/helpers.py
starlit/ui/styles.py
starlit/utils/__init__.py
starlit/utils/system_utils.py
starlit_cli-0.3.0.dist-info/METADATA
starlit_cli-0.3.0.dist-info/WHEEL
starlit_cli-0.3.0.dist-info/entry_points.txt
starlit_cli-0.3.0.dist-info/RECORD
