Metadata-Version: 2.4
Name: starlit-cli
Version: 0.3.0
Summary: A minimal, cute and customizable weather cli
Author: ashuhlee
Requires-Python: >=3.10,<4.0
Classifier: Programming Language :: Python :: 3
Classifier: Programming Language :: Python :: 3.10
Classifier: Programming Language :: Python :: 3.11
Classifier: Programming Language :: Python :: 3.12
Classifier: Programming Language :: Python :: 3.13
Classifier: Programming Language :: Python :: 3.14
Requires-Dist: python-dotenv
Requires-Dist: requests
Requires-Dist: rich
Requires-Dist: rich-color-ext (==0.1.4)
Requires-Dist: rich-gradient (==0.3.6)
Requires-Dist: terminaltexteffects
Project-URL: Homepage, https://github.com/ashuhlee/starlit
Project-URL: Repository, https://github.com/ashuhlee/starlit
